mcp_tools_math/__init__.py
mcp_tools_math/main.py
mcp_tools_math/mcp_tools_math.py
mcp_math_srinivas-0.1.0.dist-info/METADATA
mcp_math_srinivas-0.1.0.dist-info/WHEEL
mcp_math_srinivas-0.1.0.dist-info/top_level.txt
mcp_math_srinivas-0.1.0.dist-info/RECORD
